AUTHORS.txt
CHANGELOG.txt
FAQ.txt
INSTALL.txt
LICENCE.txt
README.txt
THANKS.txt
TODO.txt
ez_setup.py
setup.py
tgcrud/__init__.py
tgcrud/command.py
tgcrud/release.py
tgcrud.egg-info/PKG-INFO
tgcrud.egg-info/SOURCES.txt
tgcrud.egg-info/dependency_links.txt
tgcrud.egg-info/entry_points.txt
tgcrud.egg-info/paster_plugins.txt
tgcrud.egg-info/requires.txt
tgcrud.egg-info/sqlobject.txt
tgcrud.egg-info/top_level.txt
tgcrud.egg-info/zip-safe
tgcrud/templates/__init__.py
tgcrud/templates/crud/+modelpackage+/__init__.py_tmpl
tgcrud/templates/crud/+modelpackage+/templates/__init__.py_tmpl
tgcrud/templates/crud/+modelpackage+/templates/form.kid_tmpl
tgcrud/templates/crud/+modelpackage+/templates/list.kid_tmpl
tgcrud/templates/crud/+modelpackage+/templates/master.kid
tgcrud/templates/crud/+modelpackage+/templates/show.kid_tmpl
tgcrud/templates/crudsa/+modelpackage+/controllers.py_tmpl
tgcrud/templates/crudso/+modelpackage+/controllers.py_tmpl