Metadata-Version: 1.0
Name: tgcrud
Version: 1.0.2
Summary: Genrate CRUD interface in TurboGears
Home-page: http://docs.turbogears.org/1.0/CRUDTemplate
Author: Fred Lin
Author-email: gasolin+tg@gmail.com
License: UNKNOWN
Download-URL: http://www.python.org/pypi/tgcrud/
Keywords: turbogears.command
Platform: UNKNOWN
Classifier: Development Status :: 4 - Beta
Classifier: Operating System :: OS Independent
Classifier: Programming Language :: Python
Classifier: Topic :: Software Development :: Libraries :: Python Modules
Classifier: Framework :: TurboGears
